traceipy/__init__.py
traceipy/models/__init__.py
traceipy/models/stats_models.py
traceipy/trace_decorator/__init__.py
traceipy-0.1.0.dist-info/METADATA
traceipy-0.1.0.dist-info/WHEEL
traceipy-0.1.0.dist-info/top_level.txt
traceipy-0.1.0.dist-info/RECORD
