Metadata-Version: 2.4
Name: traceipy
Version: 0.1.0
Summary: Traceipy is a Python tracing and profiling toolkit that provides clear, detailed insights into code execution to help you identify performance bottlenecks.
Author: Deban Kumar Sahu
Project-URL: Repository, https://github.com/DebanKsahu/traceipy
Requires-Python: >=3.12
Requires-Dist: rich>=14.1.0
Requires-Dist: sortedcontainers>=2.4.0
Requires-Dist: yappi>=1.6.10
